<?xml encoding="UTF-8" version="1.0"?>
<actions>
<action>
	<icon>utilities-terminal</icon>
	<name>Terminal</name>
	<unique-id>1464040688881025-2</unique-id>
	<command>sh -c &quot;cd %f &amp;&amp; urxvt&quot;</command>
	<description>Open a shell here</description>
	<patterns>*</patterns>
	<startup-notify/>
	<directories/>
</action>
<action>
	<icon></icon>
	<name>Extract</name>
	<unique-id>1465069431065635-2</unique-id>
	<command>atool -x %F</command>
	<description>Extract an archive</description>
	<patterns>*.tar.gz;*.tgz;*.tar.bz;*.tbz;*.tar.bz2;*.tbz2;*.tar.Z;*.tZ;*.tar.lzo;*.tzo;*.tar.lz;*.tlz;*.tar.xz;*.txz;*.tar.7z;*.t7z;*.tar;*.zip;*.jar;*.war;*.rar;*.lha;*.lzh;*.7z;*.alz;*.ace;*.a;*.arj;*.arc;*.rpm;*.deb;*.cab;*.gz;*.bz;*.bz2;*.Z;*.lzma;*.lzo;*.lz;*.xz;*.rz;*.lrz;*.7z;*.cpio</patterns>
	<other-files/>
</action>
<action>
	<icon></icon>
	<name>Purge</name>
	<unique-id>1506465838589602-6</unique-id>
	<command>shred -u %F</command>
	<description>Securely erase a file</description>
	<patterns>*</patterns>
	<audio-files/>
	<image-files/>
	<other-files/>
	<text-files/>
	<video-files/>
</action>
</actions>
